bosque/__init__.py
bosque/py.typed
bosque-0.1.0.dist-info/LICENSE
bosque-0.1.0.dist-info/WHEEL
bosque-0.1.0.dist-info/METADATA
bosque-0.1.0.dist-info/RECORD
