Metadata-Version: 2.1
Name: bosque
Version: 0.1.0
Summary: Bosque
Home-page: https://github.com/perdy/bosque
License: Apache-2.0
Keywords: machine-learning,ml,ml-ops,mlops,storage,model,mlflow,dvc,tensorflow,pytorch,sklearn
Author: José Antonio Perdiguero López
Author-email: perdy@perdy.io
Requires-Python: >=3.7,<3.12
Classifier: Development Status :: 5 - Production/Stable
Classifier: Intended Audience :: Developers
Classifier: License :: OSI Approved :: Apache Software License
Classifier: Programming Language :: Python :: 3
Classifier: Programming Language :: Python :: 3.7
Classifier: Programming Language :: Python :: 3.8
Classifier: Programming Language :: Python :: 3.9
Classifier: Programming Language :: Python :: 3.10
Classifier: Programming Language :: Python :: 3.11
Classifier: Topic :: Software Development
Classifier: Topic :: Software Development :: Libraries
Classifier: Topic :: Software Development :: Libraries :: Application Frameworks
Project-URL: Repository, https://github.com/perdy/bosque
